werkzeug_auth_middleware/__init__.py
werkzeug_auth_middleware/middlewares.py
werkzeug_auth_middleware-0.1.2.dist-info/WHEEL
werkzeug_auth_middleware-0.1.2.dist-info/METADATA
werkzeug_auth_middleware-0.1.2.dist-info/RECORD
